gspreadplusplus/__init__.py
gspreadplusplus/_version.py
gspreadplusplus/core.py
gspreadplusplus/functions.py
gspreadplusplus/operations.py
gspreadplusplus/utils.py
gspreadplusplus-5.0.0.dist-info/LICENSE
gspreadplusplus-5.0.0.dist-info/METADATA
gspreadplusplus-5.0.0.dist-info/WHEEL
gspreadplusplus-5.0.0.dist-info/top_level.txt
gspreadplusplus-5.0.0.dist-info/RECORD
