Metadata-Version: 2.1
Name: gspreadplusplus
Version: 5.0.0
Summary: Enhanced Google Sheets operations with advanced data type handling
Home-page: https://github.com/daniel-simanek/gspreadplusplus
Author: Daniel Simanek
Author-email: daniel.simanek@decathlon.com
Classifier: Development Status :: 5 - Production/Stable
Classifier: Intended Audience :: Developers
Classifier: Programming Language :: Python :: 3
Classifier: Programming Language :: Python :: 3.7
Classifier: Programming Language :: Python :: 3.8
Classifier: Programming Language :: Python :: 3.9
Classifier: Programming Language :: Python :: 3.10
Classifier: License :: OSI Approved :: MIT License
Classifier: Operating System :: OS Independent
Classifier: Topic :: Office/Business :: Financial :: Spreadsheet
Classifier: Topic :: Software Development :: Libraries :: Python Modules
Requires-Python: >=3.7
License-File: LICENSE
Requires-Dist: gspread>=5.0.0
Requires-Dist: google-auth>=2.0.0
Requires-Dist: pyspark>=3.0.0
Requires-Dist: pandas>=1.0.0
